<?xml version="1.0" encoding="UTF-8"?>
<?xml-stylesheet media="screen"              title="Dictionary view"   href="../../giella-core/dicts/scripts/gt_dictionary_XXE.css"     type="text/css"?>
<?xml-stylesheet media="screen"              title="Hierarchical view" href="../../giella-core/dicts/scripts/gt_dictionary_XXE_alt.css" type="text/css" alternate="yes" ?>
<?xml-stylesheet media="print,tv,projection" title="Dictionary view"   href="../../giella-core/dicts/scripts/gt_dictionary.css"         type="text/css"?>
<?xml-stylesheet media="print,tv,projection" title="Hierarchical view" href="../../giella-core/dicts/scripts/gt_dictionary_alt.css"     type="text/css" alternate="yes" ?>
<r id="mdfrus" xml:lang="mdf">
   <e>
      <lg>
         <l pos="Pcle">а</l>
      </lg>
      <mg><tg xml:lang="rus">
            <t>II частица побуд., вопр.</t>
         </tg>;<xg>
            <x>тядяй а тядяй, кие сась?</x>
            <xt xml:lang="rus">мама, а мама, кто пришёл?</xt>
         </xg></mg>
   </e>
   <e>
      <lg>
         <l pos="Pcle">аба</l>
      </lg>
      <mg>частица <range>диал.</range> разве, или</mg>
   </e>
   <e>
      <lg>
         <l pos="Pcle">ага ага</l>
      </lg>
      <mg><tg xml:lang="rus">
            <t>частица прост. выражает согласие, подтверждение</t>
         </tg>;<xg>
            <x1>саят ширезон? - ага придёшь ко мне? - ага</x1>
         </xg></mg>
   </e>
   <e>
      <lg>
         <l pos="Pcle">али</l>
      </lg>
      <mg>
         <tg xml:lang="rus">
            <t>частица разве, или</t>
         </tg>
         <xg>
            <x src="М. Бебан, Тундань нармотть">Ули алиаш мзяровок ярмак кассаса?</x>
            <xt xml:lang="rus">Есть ли сколько-нибудь денег в кассе или нет?</xt>
         </xg>
      </mg>
   </e>
   <e>
      <lg>
         <l pos="Pcle">аньцек</l>
      </lg>
      <mg>
         <tg xml:lang="rus">
            <t>частица огранич. только, лишь</t>
         </tg>
         <xg>
            <x src="Тяшттне">Пиндолдыхть крфазь, мзярдонга аф эжендихть, аньцек шить эзда кяшендихть</x>
            <xt xml:lang="rus">Блестят и мерцают, никогда не нагреваются, лишь от солнца прячутся (Звёзды)</xt>
         </xg>
      </mg>
   </e>
   <e>
      <lg>
         <l pos="Pcle">афи</l>
      </lg>
      <mg><tg xml:lang="rus">
            <t>частица отриц. и усил. и не ..., даже ... не</t>
         </tg>;<xg>
            <x1>афи азови даже слова не могу сказать</x1>
         </xg></mg>
   </e>
   <e>
      <lg>
         <l pos="Pcle">ахаль</l>
      </lg>
      <mg>частица утв. <range>диал.</range> да</mg>
   </e>
   <e>
      <lg>
         <l pos="Pcle">аяш</l>
      </lg>
      <mg>
         <tg xml:lang="rus">
            <t>частица отриц. в знач. сказ. безл. нет</t>
         </tg>
         <xg>
            <x src="И. Кишняков, Иссась шуди Волгав">Аляц шобдава мярьгсь кудстотненди, што сон аяш кудса</x>
            <xt xml:lang="rus">Отец утром сказал, что его нет дома</xt>
         </xg>
      </mg>
   </e>
   <e>
      <lg>
         <l pos="Pcle">ба</l>
      </lg>
      <mg><tg xml:lang="rus">
            <t>I частица бы -- выражает предположение, пожелание, просьбу</t>
         </tg>;<xg>
            <x1>ушесь кармась эшендема, тон ба куду сувалеть на дворе стало прохладно, ты бы зашёл домой</x1>
         </xg></mg>
   </e>
   <e>
      <lg>
         <l pos="Pcle">бди</l>
      </lg>
      <mg><tg xml:lang="rus">
            <t>частица бы -- выражает пожелание</t>
         </tg>;<xg>
            <x>бди няемс эстейть ня панттнень</x>
            <xt xml:lang="rus">увидеть бы самому эти горы</xt>
         </xg></mg>
   </e>
   <e>
      <lg>
         <l pos="Pcle">бта</l>
      </lg>
      <mg>
         <tg xml:lang="rus">
            <t>частица будто.== Бта няиндихтень, но коста, аф мяляфтса <Xsrc>М. Кяшкин, Курссь -- Родинась</Xsrc> Будто
            видел я тебя, но где, не помню</t>
         </tg>
      </mg>
   </e>
   <e>
      <lg>
         <l pos="Pcle">ворьть</l>
      </lg>
      <mg><tg xml:lang="rus">
            <t>частица усил. же</t>
         </tg>;<xg>
            <x>аре ворьть...</x>
            <xt xml:lang="rus">пойдём же...</xt>
         </xg></mg>
   </e>
   <e>
      <lg>
         <l pos="Pcle">вроди</l>
      </lg>
      <mg><tg xml:lang="rus">
            <t>частица вроде - указывает на предположительность высказывания, на сомнение в достоверности чего-либо</t>
         </tg>;<xg>
            <x>сон вроди сяряди</x>
            <xt xml:lang="rus">он вроде болеет</xt>
         </xg>;<xg>
            <x>вроди афи якаме тоза вроде</x>
            <xt xml:lang="rus">бы и не ходили туда</xt>
         </xg></mg>
   </e>
   <e>
      <lg>
         <l pos="Pcle">всё-таки</l>
      </lg>
      <mg><tg xml:lang="rus">
            <t>частица всё-таки - употребляется для выражения возражения, противопоставления, а также для усиления
            значения высказываемого</t>
         </tg>;<xg>
            <x>всё-таки мон мархтонза аф согласнаян</x>
            <xt xml:lang="rus">всё-таки я сним не согласен</xt>
         </xg></mg>
   </e>
   <e>
      <lg>
         <l pos="Pcle">голь</l>
      </lg>
      <mg>
         <tg xml:lang="rus">
            <t>частица огранич. 1) всё только и, то и дело </t>
         </tg>
      </mg>
      <mg><variants>
            <l_syn>аньцек</l_syn>
         </variants>;<xg>
            <x>голь минць илядоме</x>
            <xt xml:lang="rus">только мы остались</xt>
         </xg></mg>
   </e>
   <e>
      <lg>
         <l pos="Pcle">да</l>
      </lg>
      <mg><tg xml:lang="rus">
            <t>II частица да - 1) усил. придаёт высказыванию больше силы, выразительности</t>
         </tg>;<xg>
            <x>мезевок да рамай!</x>
            <xt xml:lang="rus">что-нибудь да купит</xt>
         </xg>;<xg>
            <x>да тон нинге удат!</x>
            <xt xml:lang="rus">да ты ещё спишь!</xt>
         </xg>;<xg>
            <x>да тяфта ли ульсь? да так</x>
            <xt xml:lang="rus">ли было? утв. выражает согласие, утверждение</xt>
         </xg>;<xg>
            <x>мольхтяда вири пангонкса? -- да, мольхтяма пойдёте</x>
            <xt xml:lang="rus">в лес за грибами? - да пойдём</xt>
         </xg></mg>
      <mg>вопр. употребляется при желании получить подтверждение чему-либо в значении: неужели, разве, не так ли; тон
      ведь саят инжикс? - да? ты ведь приведёшь в гости? - да?; сембонь лувить! - да? всё прочитал! - да? </mg>
      <mg><tg xml:lang="rus">
            <t> употребляется в начале речи при перемены темы, при вспоминании о чём-либо</t>
         </tg>;<xg>
            <x>да, тон аф пяк лац тиеть</x>
            <xt xml:lang="rus">да, ты не очень красиво поступил</xt>
         </xg>;<xg>
            <x1>да, меляфтсайне ня ломаттнень да, я запомню этих людей</x1>
         </xg>;<xg>
            <x1>да, тонь мяльцель молемс куду, ты хотел идти домой.</x1>
         </xg><xg>
            <x src="П. Левчаев, Стирнят-якстернят">-- Да, моряса, цёрай, сиредень и вов тячиень шить эзда сявомок кудса
            ульхть азорсь тонць...</x>
            <xt xml:lang="rus">-- Да, чувствую, сынок, состарился я, и вот сегодняшнего дня хозяином дома будь ты
            сам</xt>
         </xg></mg>
      <mg><tg xml:lang="rus">
            <t> при отклике употребляется с вопросительной интонацией</t>
         </tg>;<xg>
            <x1>ялгай! -- Да? -- Тонга молят вели? дружище! -- Да? -- И ты едишь в село?</x1>
         </xg></mg>
      <mg>употребляется для выражения недоверия в значении: как же, как бы не так; кандан тейть марьхть? -- Да, кандат!
      я принесу тебе яблоки! -- Да уж, принесёшь!</mg>
   </e>
   <e>
      <lg>
         <l pos="Pcle">давай</l>
      </lg>
      <mg><tg xml:lang="rus">
            <t>давай -- 1) частица побуд. употребляется как понуждение к действию</t>
         </tg>;<xg>
            <x>-- давай стяк ни, стак</x>
            <xt xml:lang="rus">- давай вставай же, вставай</xt>
         </xg></mg>
      <mg>
         <tg xml:lang="rus">
            <t>повел. выражает приглашение к совместному действию</t>
         </tg>
         <xg>
            <x src="П. Левчаев, Стирнят-якстернят">Давай эшелятама нинге весть марса...</x>
            <xt xml:lang="rus">Давай ещё раз искупаемся вместе...</xt>
         </xg>
      </mg>
      <mg><tg xml:lang="rus">
            <t> повел. в значен. начал, принялся, стал</t>
         </tg>;<xg>
            <x1>ну давай сонь пиксомс! ну и давай его бить!</x1>
         </xg></mg>
   </e>
   <e>
      <lg>
         <l pos="Pcle">дель</l>
      </lg>
      <mg>частица отриц. <range>Т. Потьм.</range> не; дель токсе тя книгать не трогали они эту книгу</mg>
   </e>
   <e>
      <lg>
         <l pos="Pcle">дямаль</l>
      </lg>
      <mg>частица отриц. <range>Булд.</range> не следовало бы, не надо бы; дямаль корхта тянь колга не следовало бы
      говорить об этом</mg>
   </e>
   <e>
      <lg>
         <l pos="Pcle">дяряй</l>
      </lg>
      <mg>
         <tg xml:lang="rus">
            <t>частица разве, неужели</t>
         </tg>
      </mg>
   </e>
   <e>
      <lg>
         <l pos="Pcle">жа</l>
      </lg>
      <mg><tg xml:lang="rus">
            <t>частица 1) усил. же, именно, ведь - употребляется для выделения, подчёркивания слова, после которого
            ставится</t>
         </tg>;<xg>
            <x>мзярда жа сон сай</x>
            <xt xml:lang="rus">когда же он придёт?</xt>
         </xg></mg>
      <mg><tg xml:lang="rus">
            <t> подчёркивает одинаковость, постоянство предмета или явления</t>
         </tg>;<xg>
            <x>куду сань сяка жа машинать мархта</x>
            <xt xml:lang="rus">домой вернулсяч на той же машине.</xt>
         </xg><xg>
            <x src="Из сказки">Мольсь сон сяка жа васту, музе ся эрьхть</x>
            <xt xml:lang="rus">Пришёл он в то же место, нашёл то озеро</xt>
         </xg></mg>
   </e>
   <e>
      <lg>
         <l pos="Pcle">и</l>
      </lg>
      <mg><tg xml:lang="rus">
            <t>частица усил.</t>
         </tg>;<xg>
            <x1>и тонга сать! и ты тоже пришёл!</x1>
         </xg>; кяжиянь: и цебярь валга ша мялезе азомс обиделся: и доброго слова не хочу сказать </mg>
   </e>
   <e>
      <lg>
         <l pos="Pcle">изь</l>
      </lg>
      <mg><tg xml:lang="rus">
            <t>частица отриц. не - употребляется только с глаголами</t>
         </tg>;<xg>
            <x>изень, изеть, изь яка</x>
            <xt xml:lang="rus">я [ты, он] не ходил</xt>
         </xg>;<xg>
            <x1>тейнза изь шарьхкодев он не сумел понять</x1>
         </xg>;<xg>
            <x1>изь кенере ое не успел</x1>
         </xg></mg>
   </e>
   <e>
      <lg>
         <l pos="Pcle">или</l>
      </lg>
      <mg><tg xml:lang="rus">
            <t>частица вопр. разве, неужели</t>
         </tg>;<xg>
            <x1>или тянь колга мезевок ашеть куле? или ты об этом ничего не слышал?</x1>
         </xg></mg>
   </e>
   <e>
      <lg>
         <l pos="Pcle">ина</l>
      </lg>
      <mg><tg xml:lang="rus">
            <t>частица 1) усил. же - употребляется для усиления значения слова</t>
         </tg>;<xg>
            <x>корхтак ина</x>
            <xt xml:lang="rus">говори же</xt>
         </xg>;<xg>
            <x>архт ина лавкав кшинкса иди</x>
            <xt xml:lang="rus">же в магазин за хлебом</xt>
         </xg></mg>
      <mg><tg xml:lang="rus">
            <t> так</t>
         </tg>;<xg>
            <x1>ванды ина сак ширезонк так завтра приходи к нам</x1>
         </xg></mg>
      <mg><tg xml:lang="rus">
            <t> утв. ладно</t>
         </tg>;<xg>
            <x>мон ина аф молян</x>
            <xt xml:lang="rus">ладно, я не пойду</xt>
         </xg></mg>
   </e>
   <e>
      <lg>
         <l pos="Pcle">кали</l>
      </lg>
      <mg>
         <tg xml:lang="rus">
            <t>частица неужели</t>
         </tg>
         <xg>
            <x>Кали ашезь шарьхкоде? неужели</x>
            <xt xml:lang="rus">он не не понял?</xt>
         </xg>
      </mg>
   </e>
   <e>
      <lg>
         <l pos="Pcle">кати</l>
      </lg>
      <mg><tg xml:lang="rus">
            <t>частица неопр. неизвестно, не знаю</t>
         </tg>;<xg>
            <x1>молят куду? - кати пойдёшь домой - не знаю</x1>
         </xg>;<xg>
            <x>кати сай тячи стирезе, кати аф ...</x>
            <xt xml:lang="rus">неизвестно, приедет сегодня моя дочь, или нет...</xt>
         </xg></mg>
   </e>
   <e>
      <lg>
         <l pos="Pcle">катк</l>
      </lg>
      <mg>
         <tg xml:lang="rus">
            <t>частица пусть, пускай</t>
         </tg>
         <xg>
            <x src="М. Бебан, Тундань нармотть">Катк лучи шумбраста няйсамазь</x>
            <xt xml:lang="rus">Пусть лучше увидят меня здоровым</xt>
         </xg>
      </mg>
   </e>
   <e>
      <lg>
         <l pos="Pcle">клёк</l>
      </lg>
      <mg>
         <tg xml:lang="rus">
            <t>частица усил. самый, наи-</t>
         </tg>
         <xg>
            <x src="А. Мокшони, Виде киге">Клёк инголи лиссь работама комсомолка Машась</x>
            <xt xml:lang="rus">Самой первой вышла на работу комсомолка Маша</xt>
         </xg>
      </mg>
   </e>
   <e>
      <lg>
         <l pos="Pcle">апак</l>
      </lg>
      <mg><tg xml:lang="rus">
            <t>частица отриц. образует прилагательные и наречия </t>
         </tg><ltgt/><xg>
            <x>апак аделак</x>
            <xt xml:lang="rus"> незавершённый</xt>
         </xg>;<xg>
            <x>апак арьсек</x>
            <xt xml:lang="rus"> а) безрассудно, легкомысленно</xt>
         </xg>;<xg>
            <x>апак арьсек кундамс тевс</x>
            <xt xml:lang="rus"> безрассудно взяться за дело б) безрассудный, легкомысленный</xt>
         </xg>;<xg>
            <x>апак арьсек прянь</x>
            <xt xml:lang="rus">вятема легкомысленное поведение</xt>
         </xg>;<xg>
            <x>апак аст-содак</x>
            <xt xml:lang="rus">а) неожиданно</xt>
         </xg>;<xg>
            <x1>самс апак аст-содак а) неожиданно</x1>
         </xg>;<xg>
            <x>самс апак аст-содак прийти</x>
            <xt xml:lang="rus">неожиданно б) неизвестный, незнакомый.</xt>
         </xg><xg>
            <x src="П. Левчаев, Стирнят-якстернят">Пади, коса-коса апак аст-содак вастса наксадсть ни пакарензовок?</x>
            <xt xml:lang="rus">Можеть быть, где-нибудь в незнакомом краю уже истлели его кости?</xt>
         </xg>;<xg>
            <x1>апак ватт несмотря, невзирая, вопреки</x1>
         </xg>;<xg>
            <x>апак ватт мезеньге лангс</x>
            <xt xml:lang="rus">несмотря ни на что</xt>
         </xg>;<xg>
            <x>апак визть</x>
            <xt xml:lang="rus">а) беззастенчиво</xt>
         </xg>;<xg>
            <x1>васкафнемс апак визть лгать беззастенчиво б) беззастенчивый</x1>
         </xg>;<xg>
            <x1>апак визтть васькафнема беззастенчивая ложь</x1>
         </xg>;<xg>
            <x>апак каштортт тихо,</x>
            <xt xml:lang="rus">молча, затаив дыхание.</xt>
         </xg><xg>
            <x src="Т. Кирдяшкин, Кели Мокша">Таргамдост меле, местьке апак каштортт, сембе срадсть... удома</x>
            <xt xml:lang="rus">Покурив, все молча... разошлись спать</xt>
         </xg>;<xg>
            <x1>апак корхтак а) молча, беспрекословно</x1>
         </xg>;<xg>
            <x>тумс апак корхтак уйти</x>
            <xt xml:lang="rus">молча б) молчаливый, беспрекословный</xt>
         </xg>;<xg>
            <x1>апак корхтак кулхцондома беспрекословное подчинение</x1>
         </xg>;<xg>
            <x>апак лотксек</x>
            <xt xml:lang="rus">без умолку</xt>
         </xg>;<xg>
            <x1>бесперебойно, беспрерывно, непрерывно</x1>
         </xg>;<xg>
            <x1>работамс апак лотксек работать бесперебойно</x1>
         </xg>;<xg>
            <x>корхнемс апак лотксек</x>
            <xt xml:lang="rus">болтать без умолку</xt>
         </xg>;<xg>
            <x1>агрегатсь работась апак лотксек агрегат работал беспрерывно</x1>
         </xg>;<xg>
            <x>апак наказак а)</x>
            <xt xml:lang="rus">безнаказанно б) безнаказанный</xt>
         </xg>;<xg>
            <x1>апак наказак поступка безнаказанный поступок</x1>
         </xg>;<xg>
            <x1>апак няйхть а) за глаза</x1>
         </xg>;<xg>
            <x>корхтамс апак няйхть говорить</x>
            <xt xml:lang="rus">за глаза б) незаметно</xt>
         </xg>;<xg>
            <x1>ётамс апак няйхть пройти незаметно</x1>
         </xg>;<xg>
            <x>апак полафтт</x>
            <xt xml:lang="rus">а) бессменно</xt>
         </xg>;<xg>
            <x>апак полафт работать</x>
            <xt xml:lang="rus">бессменно б) бессменный</xt>
         </xg>;<xg>
            <x>апак пункстак</x>
            <xt xml:lang="rus">а) нараспашку.</xt>
         </xg><xg>
            <x src="Н. Живайкина, кяшф сёрмат">Ушеса цят моли якшамоль, сякокс кой-кит алятнень эзда якасть пуняньапак
            пункстак</x>
            <xt xml:lang="rus">На улице был трескучий мороз, но кое-кто из мужчин ходил нараспашку б) распахнутый,
            незастёгнутый</xt>
         </xg>;<xg>
            <x1>апак пункстак ор распахнутая шуба</x1>
         </xg>;<xg>
            <x1>апак сергять а) без приглашения</x1>
         </xg>;<xg>
            <x1>самс апак сергятть прийти без приглашения б) незваный, непрошенный</x1>
         </xg>;<xg>
            <x1>апак сергятть инжи непрошенный гость</x1>
         </xg>;<xg>
            <x1>апак сизек а) неутомимо, безустали</x1>
         </xg>;<xg>
            <x>сон тефт тии апак сизек</x>
            <xt xml:lang="rus">он трудился неутомимо б) неутомимый</xt>
         </xg>;<xg>
            <x1>апак сизек трудендай неутомимый труженик</x1>
         </xg>;<xg>
            <x>апак содак а)</x>
            <xt xml:lang="rus">нечаянно б) незаметно</xt>
         </xg>;<xg>
            <x1>тулхмадемс апак содак толкнуть нечаянно.</x1>
         </xg><xg>
            <x src="Т. Кирдяшкин, Кели Мокша">Маря щазе оронц и апак содак тусь куду</x>
            <xt xml:lang="rus">Мария надела шубу и незаметно ушла из дома в) незнакомый, неизвестный</xt>
         </xg>;<xg>
            <x1>апак содак ломань незнакомый человек</x1>
         </xg>;<xg>
            <x1>апак сргость беспробудно</x1>
         </xg>;<xg>
            <x1>удомс апак сргость спать беспробудно</x1>
         </xg>;<xg>
            <x1>апак тертть см. апак сергятть</x1>
         </xg>;<xg>
            <x1>апак тушентт неотлучно</x1>
         </xg>;<xg>
            <x1>апак тушентт ащемс кудса неотлучно сидеть дома</x1>
         </xg>;<xg>
            <x>апак ужяльтть</x>
            <xt xml:lang="rus">нещадно, безжалостно</xt>
         </xg>;<xg>
            <x1>шись апак ужяльтть косьфнезе модать солнце нещадно сушило землю</x1>
         </xg>;<xg>
            <x>апак учт, учсек прийти</x>
            <xt xml:lang="rus">неожиданно б) неожиданный, внезапный</xt>
         </xg>;<xg>
            <x1>апак учт кулома внезапная смерть</x1>
         </xg>;<xg>
            <x>апак учт-анак</x>
            <xt xml:lang="rus">а) нежданно-негаданно.</xt>
         </xg><xg>
            <x src="Т. Кирдяшкин, Кели Мокша">Савва апак учт-анак тяшкава цебярьгодсь</x>
            <xt xml:lang="rus">Савва неожиданно очень подобрел б) нежданный</xt>
         </xg>;<xg>
            <x1>апак учт-анак куля нежданная новость</x1>
         </xg>;<xg>
            <x>апак фатяк</x>
            <xt xml:lang="rus">а) нечаянно</xt>
         </xg>;<xg>
            <x1>прафтомс апак фатяк книгать нечаянно уронить книгу б) нечаянный</x1>
         </xg>;<xg>
            <x1>апак фатяк ляцема нечаянный выстрел</x1>
         </xg>;<xg>
            <x>апак шерьхк</x>
            <xt xml:lang="rus">а) неподвижно</xt>
         </xg>;<xg>
            <x>стяда ащемс апак шерьхк</x>
            <xt xml:lang="rus">стоять неподвижно б) неподвижный</xt>
         </xg>;<xg>
            <x1>апак шерьхк ащема неподвижное состояние</x1>
         </xg>;<xg>
            <x1>апак шумнак бесшумно, без шума.</x1>
         </xg><xg>
            <x src="Валдсь">Пильгфтома-пряфтома, куду сувай апак шумнак</x>
            <xt xml:lang="rus">Без рук, без ног, в дом войдёт без шума (Свет)</xt>
         </xg>;<xg>
            <x1>апак шумордак неоконченный, незаконченный, апак шумордак тев незаконченное дело</x1>
         </xg>;<xg>
            <x>апак эльбятть а)</x>
            <xt xml:lang="rus">безошибочно, правильно, верно</xt>
         </xg>;<xg>
            <x1>задачать тиемс апак эльбятть правильно решить задачу б) безошибочный, правильный, верный</x1>
         </xg>;<xg>
            <x1>апак эльбятть арьсема правильное решение</x1>
         </xg>;<xg>
            <x>апак якак</x>
            <xt xml:lang="rus">нехоженый, неизведанный</xt>
         </xg>;<xg>
            <x>тумс апак якак киге</x>
            <xt xml:lang="rus">пойти по нехоженой тропе</xt>
         </xg>;<xg>
            <x>апак явфт а) совместно</x>
            <xt xml:lang="rus">б) нераздельный, совместный, единый</xt>
         </xg>;<xg>
            <x1>тядяти оцю павазкс ащи шабанзон мархта апак явфт эрямась большим счастьем для матери является совместная
            жизнь с детьми</x1>
         </xg>;<xg>
            <x1>апак ярхцак натощак</x1>
         </xg>;<xg>
            <x1>симомс лекарствать апак ярхцак принять лекарство натощак</x1>
         </xg></mg>
   </e>
   <e>
      <lg>
         <l pos="Pcle">кода</l>
      </lg>
      <mg><tg xml:lang="rus">
            <t>частица как - выражает удивление, негодование и т. п.</t>
         </tg>; кода сон полафтсь! как он изменился! <ltgt/><xg>
            <x>кода ина</x>
            <xt xml:lang="rus">а) какже</xt>
         </xg>;<xg>
            <x1>кода ина сёрмадомс? как же написать? б) утв. как же, обязательно</x1>
         </xg>;<xg>
            <x1>саят тячи? - кода ина! придёшь сегодня? - а как же!</x1>
         </xg>;<xg>
            <x1>аш кода нельзя</x1>
         </xg>;<xg>
            <x>аш кода аф молемс</x>
            <xt xml:lang="rus">как быто ни было</xt>
         </xg>;<xg>
            <x1>кода аф кода, а синь эрявихть мирендафтомс как бы то ни было, а их надо помирить.</x1>
         </xg><xg>
            <x src="Шинь стяма">-- Кода аф кода, а доходнай статьясь, арьсесь Пулоксов эсь пачканза</x>
            <xt xml:lang="rus">-- Как бы то ни было, а статья доходная, -- думал про себя Пулоксов</xt>
         </xg>;<xg>
            <x>кода ашезь [ашеме...]</x>
            <xt xml:lang="rus">как он ни, как мы ни и т. д.</xt>
         </xg>;<xg>
            <x>кода ашезь эряскода, поездти сяка поздазе как</x>
            <xt xml:lang="rus">ни торопился, к поезду всё равно опоздал</xt>
         </xg>;<xg>
            <x>кода бзнай каруса медь как от козла</x>
            <xt xml:lang="rus">молока (букв. как от жужжащей мухи мёд)</xt>
         </xg>;<xg>
            <x1>кода вай ланга как по маслу - гладко, без затруднений, легко.</x1>
         </xg>[] Тулають пароль мялезонза: тевсь мольсь, кода вай ланга <Xsrc>П. Левчаев, Вирст увнай</Xsrc> У тулая
      хорошо было на душе: дело шло, как по маслу; кода ведьс ванонь как в воду смотрел - как будто узнал заранее; кода
      ведьс ваясь как воду канул - исчез, пропал без бесследно; кода мярьгомс как сказать; кода онцтон (онцтонза...) как
      во сне (я, он и т. д. ) кода повсь как попало, по-всякому; щамонза ёряфтольхть кода повсь одежда его была
      разбросана как попало. []<xg>
            <x src="Ф. Атянин, Мзярда кенерихть марьхне">Ветешка минута аньцяй бабанясь сюцезень кода повсь</x>
            <xt xml:lang="rus">Минут пять старушка как огня бояться.</xt>
         </xg>[]<xg>
            <x src="С. Ларионов, Лямбе кядьса"> Степашкин рахазевсь: -- Тон, Карп максимович, кода толда пелят Леховть
            эзда </x>
            <xt xml:lang="rus"> Степашкин рассмеялся: -- Ты, Карп Максимович, как огня боишься Лехова</xt>
         </xg></mg>
   </e>
   <e>
      <lg>
         <l pos="Pcle">кодама</l>
      </lg>
      <mg><tg xml:lang="rus">
            <t>частица воскл. какой</t>
         </tg>;<xg>
            <x1>аньцек кодама петлицат аш боецнень гимнастёркаса! каких только петлиц нет на гимнастёрках бойцов!</x1>
         </xg>;<xg>
            <x>кодама тяса удома!</x>
            <xt xml:lang="rus">какой тут сон!</xt>
         </xg><ltgt/><xg>
            <x>кодама повсь разный,</x>
            <xt xml:lang="rus">всякий, какой попало.</xt>
         </xg><xg>
            <x src="В. Виард, Кешань приключениянза">Синь содасазь, што тяса лама паршида и азонкшнихть кодама повсь
            баснят...</x>
            <xt xml:lang="rus">Они знают, что здесь много богатств и рассказывают всякое</xt>
         </xg>;<xg>
            <x src="Кандозь...">кодама шкай кандозе</x>
            <xt xml:lang="rus">каким ветром тебя (вас и т. д.) занесло (букв. какой бог тебя послал).</xt>
         </xg><xg>
            <x src="Л. Макулов, Мокшень стирь">"Вай-а-ай, Иван Иванович, а кодама кандонзе тяфтама погоданя!" --
            корхтась Татьяна Ивановна</x>
            <xt xml:lang="rus">"Ой, Иван Иванович, да каким ветром вас занесло в такую погоду!" -- говорила Татьяна
            Ивановна</xt>
         </xg></mg>
   </e>
   <e>
      <lg>
         <l pos="Pcle">конешна</l>
      </lg>
      <mg>
         <tg xml:lang="rus">
            <t>частица конечно, да, разумеется</t>
         </tg>
         <xg>
            <x src="М. Кяшкин">-- Можна тейне озамс? -- Конечна</x>
            <xt xml:lang="rus">-- Можно мне сесть? -- Конечно</xt>
         </xg>
      </mg>
   </e>
   <e>
      <lg>
         <l pos="Pcle">крда</l>
      </lg>
      <mg><tg xml:lang="rus">
            <t>частица в - употребляется при обозначении соотношении чисел</t>
         </tg>;<xg>
            <x>кафтонь-крда в</x>
            <xt xml:lang="rus">два раза</xt>
         </xg></mg>
   </e>
   <e>
      <lg>
         <l pos="Pcle">ладна</l>
      </lg>
      <mg><tg xml:lang="rus">
            <t>в знач. утв. частица хорошо, ладно</t>
         </tg>;<xg>
            <x1>ну ладна, тисан тонь лацот ну ладно, сделаю по-твоему</x1>
         </xg></mg>
   </e>
   <e>
      <lg>
         <l pos="Pcle">ли</l>
      </lg>
      <mg><tg xml:lang="rus">
            <t>частица I ли - 1) вопр. подчёркивает вопросительный характер предложения</t>
         </tg>;<xg>
            <x1>молят ли ульцяв? пойдёшь ли на улицу?</x1>
         </xg></mg>
      <mg><tg xml:lang="rus">
            <t> с некоторыми словами образует сочетания со значением сомнения, определённости</t>
         </tg>;<xg>
            <x1>тяфта ли тя? так ли это? вряд ли тячи саван вряд ли я смогу сегодня прийти? кржа ли кудса тевда мало ли
            дома дел</x1>
         </xg></mg>
      <mg>
         <tg xml:lang="rus">
            <t>выделяет в предложении то слово, к которому относится</t>
         </tg>
         <xg>
            <x src="С. Ларионов">Аф ли тон корхтать, штоба кадолине мархтонза ялгазень?</x>
            <xt xml:lang="rus">Не ты ли говорил, чтобы я оставил с ним друга?</xt>
         </xg>
      </mg>
   </e>
   <e>
      <lg>
         <l pos="Pcle">мле</l>
      </lg>
      <mg><tg xml:lang="rus">
            <t>частица 1) утв. да</t>
         </tg>;<xg>
            <x>-- тон молят тонафнема? - мле, молян</x>
            <xt xml:lang="rus">- ты пойдёшь учиться? - да, пойду</xt>
         </xg></mg>
      <mg>
         <tg xml:lang="rus">
            <t>усил. же</t>
         </tg>
         <xg>
            <x src="М. Кяшкин, Мзярда перьфкат ялгат">А кода мле, вдь закоттнень аф минь сёрматкшнесаськ</x>
            <xt xml:lang="rus">А как же, ведь законы не мы издаём</xt>
         </xg>
      </mg>
   </e>
   <e>
      <lg>
         <l pos="Pcle">моли</l>
      </lg>
      <mg>
         <tg xml:lang="rus">
            <t>частица утв. идёт!, ладно!, пойдёт!, подойдёт!</t>
         </tg>
      </mg>
   </e>
   <e>
      <lg>
         <l pos="Pcle">мяк</l>
      </lg>
      <mg><tg xml:lang="rus">
            <t>частица усил. как раз, досамого (самой)</t>
         </tg>;<xg>
            <x1>ёрдамс кевть мяк вельхксти добросить камень до самой крыши</x1>
         </xg>;<xg>
            <x1>сёрось саты мяк тундати урожая хватит до самой вексны</x1>
         </xg></mg>
   </e>
   <e>
      <lg>
         <l pos="Pcle">мяле</l>
      </lg>
      <mg><tg xml:lang="rus">
            <t>частица утв. да</t>
         </tg>;<xg>
            <x1>-- тяфта што ли тевсель? - мяле, мяле - так, что ли, было дело? - да, да</x1>
         </xg></mg>
   </e>
   <e>
      <lg>
         <l pos="Pcle">на</l>
      </lg>
      <mg><tg xml:lang="rus">
            <t>частица в знач. сказ. на - возьми, бери, получай</t>
         </tg>;<xg>
            <x>на, тейть марь</x>
            <xt xml:lang="rus">на, возьми яблоко</xt>
         </xg>;<xg>
            <x>на кантк</x>
            <xt xml:lang="rus">на, отнеси</xt>
         </xg><ltgt/><xg>
            <x1>вот тейть и на! вот тебе и на! - восклицание по поводу чего-либо неожиданного, удивительного</x1>
         </xg></mg>
   </e>
   <e>
      <lg>
         <l pos="Pcle">на-ка</l>
      </lg>
      <mg>
         <tg xml:lang="rus">
            <t>частица в знач. сказ. на-ка - возьми, бери</t>
         </tg>
         <xg>
            <x src="И. Девин, Нардише">-- На-ка, ёнь покольняй, на-ка, матаняй...</x>
            <xt xml:lang="rus">-- На-ка, моя разумница, на-ка моё золотце...</xt>
         </xg>
      </mg>
   </e>
   <e>
      <lg>
         <l pos="Pcle">нда</l>
      </lg>
      <mg>частица утв. <range>диал.</range> да - 1) выражает согласие; молят пангс? - нда пойдёшь за грибами? - да </mg>
      <mg>употребляется в повествовательной речи при передаче итогов размышления по поводу чего-либо, в значении: так,
      действительно; нда, тяфта эряфське сембе ётай да, так и вся жизнь пройдёт</mg>
   </e>
   <e>
      <lg>
         <l pos="Pcle">недань</l>
      </lg>
      <mg><tg xml:lang="rus">
            <t>частица не то, чтобы...</t>
         </tg>;<xg>
            <x1>не только бы...</x1>
         </xg>;<xg>
            <x1>цёрась недань, ласькозь тумс, вастстонзовок ашезь шерьхке парень, нето , чтобы побежать, но и с места не
            тронулся.</x1>
         </xg><xg>
            <x src="М. Бебан, Кенди медь">-- Да моньфтемон, кле, -- саразсь недань алыямс, пизотинге афоль оза</x>
            <xt xml:lang="rus">-- Да без меня, дескать, курица не только бы не снеслась, и в гнездо не села бы</xt>
         </xg></mg>
   </e>
   <e>
      <lg>
         <l pos="Pcle">нетомшта</l>
      </lg>
      <mg>
         <tg xml:lang="rus">
            <t>частица не то чтобы</t>
         </tg>
         <xg>
            <x src="М. Бебан">Ульсть, кле, оцюнясна, конат шамаснонга ашезь солафне, нетомшта добрайста пшкядельхть</x>
            <xt xml:lang="rus">Говорят, что у них были начальники, у которых на лице никогда улыбки не было, не то чтобы
            доброе слово сказать</xt>
         </xg>
      </mg>
   </e>
   <e>
      <lg>
         <l pos="Pcle">неужели</l>
      </lg>
      <mg><tg xml:lang="rus">
            <t>частица вопр. неужели</t>
         </tg>;<xg>
            <x>неужели тон сать?</x>
            <xt xml:lang="rus">неужели ты приехал?</xt>
         </xg>;<xg>
            <x>неужели тячи пизем туй?</x>
            <xt xml:lang="rus">неужели сегодня дождик пойдёт?</xt>
         </xg></mg>
   </e>
   <e>
      <lg>
         <l pos="Pcle">ни</l>
      </lg>
      <mg><tg xml:lang="rus">
            <t>частица усил. уж, уже</t>
         </tg><xg>
            <x src="М. Кяшкин, Мзярда перьфкат ялгат">Мон ни сембонь аноклайне операциять тиемс</x>
            <xt xml:lang="rus">Я уже всё приготовила для операции</xt>
         </xg>;<xg>
            <x>мон ни тумс срхкань</x>
            <xt xml:lang="rus">я уже собрался уходить</xt>
         </xg></mg>
   </e>
   <e>
      <lg>
         <l pos="Pcle">никак</l>
      </lg>
      <mg><tg xml:lang="rus">
            <t>частица никак, кажется, как будто</t>
         </tg>;<xg>
            <x>никак инжихть састь?</x>
            <xt xml:lang="rus">никак гости приехали?</xt>
         </xg></mg>
   </e>
   <e>
      <lg>
         <l pos="Pcle">нльне</l>
      </lg>
      <mg>
         <tg xml:lang="rus">
            <t>частица усил. даже</t>
         </tg>
         <xg>
            <x src="М. Безбородов, Стихт и поэмат">Мокшетнень колга атясь корхтама кармай, вайгялец трнай, нльне,
            аварди...</x>
            <xt xml:lang="rus">Начнёт старик говорить о мокше, голос задрожит, даже плачет.</xt>
         </xg>
         <xg>
            <x src="П. Левчаев, Стирнят-якстернят">Пашу сяшкава тянь ашезе учсе, нльне васенда сонцьке абондсь... </x>
            <xt xml:lang="rus"> Паша настолько не ожидал этого, что даже вначале и сам растерялся</xt>
         </xg>
      </mg>
   </e>
   <e>
      <lg>
         <l pos="Pcle">ну</l>
      </lg>
      <mg><tg xml:lang="rus">
            <t>частица вопр. ну</t>
         </tg>;<xg>
            <x>да ну? тя аф виде?</x>
            <xt xml:lang="rus">да ну? это же неправда?</xt>
         </xg></mg>
   </e>
   <e>
      <lg>
         <l pos="Pcle">пади</l>
      </lg>
      <mg>
         <tg xml:lang="rus">
            <t>вводн. может, может быть, должно быть</t>
         </tg>
         <xg>
            <x src="И. Кишняков, Иссась шуди Волгав">Пади, кивок вешендьсамазь?</x>
            <xt xml:lang="rus">Может, кто-нибудь ищет нас?</xt>
         </xg>
      </mg>
      <mg><tg xml:lang="rus">
            <t> частица утв. наверное</t>
         </tg>;<xg>
            <x1>-- саят? - пади придёшь? - наверное</x1>
         </xg></mg>
   </e>
   <e>
      <lg>
         <l pos="Pcle">пароль</l>
      </lg>
      <mg><tg xml:lang="rus">
            <t>частица со знач. Желательности хорошо бы</t>
         </tg>;<xg>
            <x1>пароль ваймамс хорошо бы отдохнуть</x1>
         </xg>;<xg>
            <x1>пароль эшелямс хорошо бы искупаться</x1>
         </xg></mg>
   </e>
   <e>
      <lg>
         <l pos="Pcle">пожалуйста</l>
      </lg>
      <mg>
         <tg xml:lang="rus">
            <t>частица пожалуйста - 1) форма вежливого обращения при просьбе, приказании,разрешении</t>
         </tg>
         <xg>
            <x src="М. Кяшкин, Мзярда перьфкат ялгат">Азость, пожалуйста, кода мумс колхозниконь кудонтень?</x>
            <xt xml:lang="rus">Скажите, пожалуйста, как добраться до Дома колхозника?</xt>
         </xg>
      </mg>
      <mg><tg xml:lang="rus">
            <t>форма вежливого ответа на извинение или на благодарность</t>
         </tg>;<xg>
            <x1>пасиба тейнть лезксонкса. -- Пожалуйста спасибо вам за помощь. -- Пожалуйста.</x1>
         </xg></mg>
   </e>
   <e>
      <lg>
         <l pos="Pcle">пока</l>
      </lg>
      <mg><tg xml:lang="rus">
            <t>частица прост. до свидания</t>
         </tg>;<xg>
            <x1>мон тунь..., пока! я пошёл..., пока !</x1>
         </xg></mg>
   </e>
   <e>
      <lg>
         <l pos="Pcle">пряма</l>
      </lg>
      <mg><tg xml:lang="rus">
            <t>частица при возражении</t>
         </tg>;<xg>
            <x>как же,</x>
            <xt xml:lang="rus">вот ещё</xt>
         </xg>;<xg>
            <x>тон молят ширезонза? - пряма! -</x>
            <xt xml:lang="rus">ты пойдёшь к нему? - прямо!</xt>
         </xg></mg>
   </e>
   <e>
      <lg>
         <l pos="Pcle">пчкяль</l>
      </lg>
      <mg><tg xml:lang="rus">
            <t>частица усил. приглаголах со значением желательности</t>
         </tg>;<xg>
            <x>пчкяль ярхцалень калда я</x>
            <xt xml:lang="rus">хотел бы поесть рыбы</xt>
         </xg>;<xg>
            <x1>пчкяль тонафнелень врачекс я хотел бы учиться на врача</x1>
         </xg></mg>
   </e>
   <e>
      <lg>
         <l pos="Pcle">рази</l>
      </lg>
      <mg><tg xml:lang="rus">
            <t>частица разве - 1) вопр. так ли, правда ли, что</t>
         </tg>;<xg>
            <x>рази сон сась?</x>
            <xt xml:lang="rus">разве он приехал?</xt>
         </xg></mg>
      <mg><tg xml:lang="rus">
            <t> может быть</t>
         </tg>;<xg>
            <x1>рази корхтават мархтонза? разве поговорить с ним?</x1>
         </xg></mg>
   </e>
   <e>
      <lg>
         <l pos="Pcle">роди</l>
      </lg>
      <mg>
         <tg xml:lang="rus">
            <t>частица вроде - как будто, словно</t>
         </tg>
         <xg>
            <x src="И. Девин, Нардише">Роди масторсь лазовсь пачк!</x>
            <xt xml:lang="rus">Вроде земля раздвоилась!</xt>
         </xg>
      </mg>
   </e>
   <e>
      <lg>
         <l pos="Pcle">саты</l>
      </lg>
      <mg><tg xml:lang="rus">
            <t>частица довольно, хватит</t>
         </tg>;<xg>
            <x>саты, мон сизень</x>
            <xt xml:lang="rus">хватит, я устал.</xt>
         </xg><xg>
            <x src="В. Левин, Аера варма">Саты, пленца кирнемайть</x>
            <xt xml:lang="rus">Довольно, ты долго в плену меня держал</xt>
         </xg></mg>
   </e>
   <e>
      <lg>
         <l pos="Pcle">сембоц</l>
      </lg>
      <mg>
         <tg xml:lang="rus">
            <t>частица только, не более, чем</t>
         </tg>
         <xg>
            <x src="С. Ларионов, Хрусталень пайкт">Ефим Афанасьевич Кокнаев... сембоц кафта кофт, кода сась заводу
            уноконц мархта работама</x>
            <xt xml:lang="rus">Ефим Афанасьевич кокнаев,.. всего два месяца, как приехал с внуком работать на завод</xt>
         </xg>
      </mg>
   </e>
   <e>
      <lg>
         <l pos="Pcle">сик</l>
      </lg>
      <mg>
         <tg xml:lang="rus">
            <t>частица только и </t>
         </tg>
         <xg>
            <x src="И. Кишняков, Иссась шуди Волгав">Сик морсек, кштишентть</x>
            <xt xml:lang="rus">Только и пой, пляши</xt>
         </xg>
      </mg>
   </e>
   <e>
      <lg>
         <l pos="Pcle">сикянь</l>
      </lg>
      <mg>
         <tg xml:lang="rus">
            <t>частица только бы ... , лишь бы ..</t>
         </tg>
         <xg>
            <x src="М. Бебан, Кенди медь">...и корма изь ужяльде ( Кирьхкссь), сикянь лацкас шнаволь </x>
            <xt xml:lang="rus"> ... и корм не жалел ( Воробей) , только бы его похвалили</xt>
         </xg>
      </mg>
   </e>
   <e>
      <lg>
         <l pos="Pcle">спасиба</l>
      </lg>
      <mg>
         <tg xml:lang="rus">
            <t>частица спасибо - выражение благодарности</t>
         </tg>
         <xg>
            <x src="Т. Кирдяшкин, Кели Мокша">-- Спасиба, бабай, -- отвечась Авдю</x>
            <xt xml:lang="rus">-- Спасибо, бабушка, -- ответил Авдю</xt>
         </xg>
      </mg>
   </e>
   <e>
      <lg>
         <l pos="Pcle">ся,</l>
      </lg>
      <mg>
         <tg xml:lang="rus">
            <t>-т мест. указ. тот, та, то - 1) указывает на что-либо, более отдалённое в пространстве или времени, а
            также на уже упоминавшееся в речи и уже известное и т. п</t>
         </tg>
         <xg>
            <x src="В. Лёвин, Аера варма">Ся шиста ушедсть Степанонь од эряфоц</x>
            <xt xml:lang="rus">С того дня у Степана началась новая жизнь.</xt>
         </xg>
         <xg>
            <x src="А. Мокшони, Виде киге">Но ся пинкне ётасть </x>
            <xt xml:lang="rus"> Но те времена прошли</xt>
         </xg>
      </mg>
      <mg><tg xml:lang="rus">
            <t>с усилительными частицами -вок, -ге, -ка и тот..., и та..., и то..., и те... и т. д</t>
         </tg><xg>
            <x src="П. Левчаев, Аляшка Цёрокш">А машинась вишкста гукстсь и тусь, и тусь - аньцек качамоц лядсь станцияв
            и сявок курок солась</x>
            <xt xml:lang="rus">А машина громко гугукнула и пошла, и пошла - только дым после неё остался на станции, да
            и тот быстро рассеялся. Танясь сятнендивок отвечась <Xsrc>И. Кишняков, Мзярда перьфкат ялгат</Xsrc> Таня
            ответила и тем. Сятненьге апак сялонтт аф сявсайть <Xsrc>И. Кяшкин, Цёфксне морайхть</Xsrc> И тех без ругани
            не возьмёшь. Ушедат селькоронь ёмла заметкань лувома, сятка прязт аф молихть <Xsrc>В. Радин, Сембе минь
            ломаттяма</Xsrc> Начнёшь селькоровские маленькие заметки читать, и те в голову не лезут</xt>
         </xg><ltgt/><xg>
            <x1>сянь содаец аш этого никто не знает</x1>
         </xg>;<xg>
            <x>кие тиезе тя тевть, сянь содаец аш</x>
            <xt xml:lang="rus">кто так сделал, этого никто не знает</xt>
         </xg>;<xg>
            <x1>сянь мархта мезевок аф тият этим ничего не сделаешь</x1>
         </xg>;<xg>
            <x1>сянь мархта аф сявсак этим ты его не возьмёшь</x1>
         </xg>;<xg>
            <x1>сявок видец и то правда.</x1>
         </xg><xg>
            <x src="М. Кяшкин, Мзярда перьфкат ялгат">-- Сявок видец, работамс сави ламос, -- кулевсь ялганц
            вайгялец</x>
            <xt xml:lang="rus">-- И то правда, работать придётся долго, -- раздался голос товарища</xt>
         </xg></mg>
   </e>
   <e>
      <lg>
         <l pos="Pcle">так</l>
      </lg>
      <mg><tg xml:lang="rus">
            <t>частица утв. так</t>
         </tg>;<xg>
            <x>так, тя сон</x>
            <xt xml:lang="rus">так, это он</xt>
         </xg></mg>
   </e>
   <e>
      <lg>
         <l pos="Pcle">таки</l>
      </lg>
      <mg><tg xml:lang="rus">
            <t>частица 1) всё-таки, всё же, однако</t>
         </tg>;<xg>
            <x1>таки тон аф молят? ты так и не идёшь?</x1>
         </xg></mg>
      <mg><tg xml:lang="rus">
            <t> усил. так и -- при глаголах</t>
         </tg>;<xg>
            <x>таки пачкодень ялга куду так</x>
            <xt xml:lang="rus">и дошёл я домой пешком</xt>
         </xg></mg>
   </e>
   <e>
      <lg>
         <l pos="Pcle">теконь</l>
      </lg>
      <mg>частица 1) <range>Паёв.</range> такой; теконь оцю велесь такое большое село </mg>
      <mg>
         <variants>
            <l_syn>таки</l_syn>
         </variants>
      </mg>
   </e>
   <e>
      <lg>
         <l pos="Pcle">тожа</l>
      </lg>
      <mg><tg xml:lang="rus">
            <t>частица тоже - выражает недоверчивое или отрицательное отношение к чему-либо</t>
         </tg>;<xg>
            <x>тожа ёню</x>
            <xt xml:lang="rus">тоже умник</xt>
         </xg></mg>
   </e>
   <e>
      <lg>
         <l pos="Pcle">тота</l>
      </lg>
      <mg>
         <tg xml:lang="rus">
            <t>частица то-то - подчёркивает главное в предшествующей речи в значении в том-то и дело, вот именно</t>
         </tg>
      </mg>
   </e>
   <e>
      <lg>
         <l pos="Pcle">туй</l>
      </lg>
      <mg><tg xml:lang="rus">
            <t>частица хорошо, ладно, пойдёт</t>
         </tg>;<xg>
            <x>лац тиф, туй!</x>
            <xt xml:lang="rus">хорошо сделано, пойдёт!</xt>
         </xg></mg>
   </e>
   <e>
      <lg>
         <l pos="Pcle">тык</l>
      </lg>
      <mg>
         <tg xml:lang="rus">
            <t>частица усил. так</t>
         </tg>
         <xg>
            <x src="И. Кишняков, Полю">Аляцень васьфтема - тык тон аш, Сёма цёразе савсь кучемс</x>
            <xt xml:lang="rus">Отца встречать - так тебя нет, пришлось послать сына Семёна</xt>
         </xg>
      </mg>
   </e>
   <e>
      <lg>
         <l pos="Pcle">тьки</l>
      </lg>
      <mg><tg xml:lang="rus">
            <t>частица таки - всё же, однако</t>
         </tg>;<xg>
            <x1>тьки кенерсь поезти успел таки на поезд</x1>
         </xg></mg>
   </e>
   <e>
      <lg>
         <l pos="Pcle">тят</l>
      </lg>
      <mg>
         <tg xml:lang="rus">
            <t>частица отрицат. не - употребляется с глаголами в повелительном наклонении</t>
         </tg>
         <xg>
            <x src="П. Левчаев, Аляшка цёрокш">Минць видесаськ, минць и урядасаськ, тят явсе</x>
            <xt xml:lang="rus">Сами засеем, сами и уберём, не плачь.</xt>
         </xg>
         <xg>
            <x src="П. Левчаев, Стирнят-якстернят">Ватт, мака лопаняй, тят дураскода, тят тапаря мархтост, а вешк эсь
            кицень, мук эсь вастоняцень </x>
            <xt xml:lang="rus"> Смотри, мой маковый листочек, не сойди с ума, не связывайся с ними, а найди свою дорогу,
            своё место</xt>
         </xg>
      </mg>
   </e>
   <e>
      <lg>
         <l pos="Pcle">тяты</l>
      </lg>
      <mg>
         <tg xml:lang="rus">
            <t>частица отрицат. и не - употребляется с глаголами в повелительном наклонении</t>
         </tg>
         <xg>
            <x src="Н. Учватов, Алят">Тяты корхта, Макар, мзяра ломань тя войнась юмафты</x>
            <xt xml:lang="rus">И не говори, Макар, сколько людей уносит война</xt>
         </xg>
      </mg>
   </e>
   <e>
      <lg>
         <l pos="Pcle">ужели</l>
      </lg>
      <mg><tg xml:lang="rus">
            <t>частица вопр. неужели</t>
         </tg>;<xg>
            <x>ужели сон мрдай?</x>
            <xt xml:lang="rus">неужели он вернётся?</xt>
         </xg><xg>
            <x src="Л. Макулов, Мокшень стирь">Ужели сон жив?</x>
            <xt xml:lang="rus">Неужели он жив?</xt>
         </xg></mg>
   </e>
   <e>
      <lg>
         <l pos="Pcle">уш</l>
      </lg>
      <mg><tg xml:lang="rus">
            <t>частица усил. уптребляется для подчёркивания, усиления отдельного слова или целого высказывания</t>
         </tg>;<xg>
            <x1>кодама уш поэтан какой уж я поэт</x1>
         </xg></mg>
   </e>
   <e>
      <lg>
         <l pos="Pcle">хоть</l>
      </lg>
      <mg><tg xml:lang="rus">
            <t>частица усилит. входит в состав словосочетаний</t>
         </tg>;<xg>
            <x1>хоть кие хоть кто - всякий, любой</x1>
         </xg>;<xg>
            <x>хоть мезе хоть что</x>
            <xt xml:lang="rus">- всё, что угодно</xt>
         </xg>;<xg>
            <x>хоть коса хоть где</x>
            <xt xml:lang="rus">- в любом месте</xt>
         </xg>;<xg>
            <x>хоть ков хоть</x>
            <xt xml:lang="rus">куда - всюду</xt>
         </xg>;<xg>
            <x1>хоть кодама хоть какой-нибудь - безразлично какой</x1>
         </xg>;<xg>
            <x1>хоть косовок хоть где-нибудь - безразлично где.</x1>
         </xg><xg>
            <x src="П. Левчаев, Вирсь увнай">Хоть косовок корожсь ювадель или кодама нармонь вяшкозеволь</x>
            <xt xml:lang="rus">Хоть где-нибудь сова подала бы голос или какая другая птица засвистела бы </xt>
         </xg><ltgt/><xg>
            <x1>хоть ба хоть бы - хорошо бы</x1>
         </xg>;<xg>
            <x1>хоть ба лангозонк варжакстоль хоть бы взглянул на нас</x1>
         </xg>;<xg>
            <x>хоть ба ваймамс</x>
            <xt xml:lang="rus">хоть бы отдохнуть</xt>
         </xg></mg>
   </e>
   <e>
      <lg>
         <l pos="Pcle">ця</l>
      </lg>
      <mg><tg xml:lang="rus">
            <t>частица на - вот, возьми</t>
         </tg>;<xg>
            <x>ця калаця</x>
            <xt xml:lang="rus">на калач.</xt>
         </xg><xg>
            <x src="П. Левчаев, Аляшка цёрокш">Ця, Матя, оргалдыть салу ведняса</x>
            <xt xml:lang="rus">На, Мотя, сполосни в солёной водице</xt>
         </xg></mg>
   </e>
   <e>
      <lg>
         <l pos="Pcle">цяда</l>
      </lg>
      <mg>
         <tg xml:lang="rus">
            <t>частица нате - вот, возьмите</t>
         </tg>
         <xg>
            <x>Цяда,</x>
            <xt xml:lang="rus">сявость</xt>
         </xg>
         <xg>
            <x src="П. Левчаев, Аляшка цёрокш">; вачи пеконте - ярхцада </x>
            <xt xml:lang="rus"> Нате, возьмите: проголодаетесь - съедите</xt>
         </xg>
      </mg>
   </e>
   <e>
      <lg>
         <l pos="Pcle">эва</l>
      </lg>
      <mg>частица <range>диал.</range> вон, вот - указывает на какой-либо предмет; эва и лихтибряняське вон и родничок
      </mg>
   </e>
   <e>
      <lg>
         <l pos="Pcle">эвон</l>
      </lg>
      <mg>частица <range>Зуб.-пол.</range> вон - указывает на происходящее в удалении; эвон сон сай вон он идёт</mg>
   </e>
   <e>
      <lg>
         <l pos="Pcle">эди</l>
      </lg>
      <mg>частица да и. Эди маштоль пичефксозе <Xsrc>В. Мокшони, Виде киге</Xsrc> Да и горе моё кончилось бы. -- Эрь,
      тиезе тя тевть... народсь мярьгсь, -- эди - сялдаз ланга Лефть: -- да ворть ни! Месть шорсят? <Xsrc>М. Бебан,
      Кенди медь</Xsrc> -- Ну это его рук дело... -- сказал народ, да и - по шее Льва: -- уходи уж! Чего мешаешь?</mg>
   </e>
   <e>
      <lg>
         <l pos="Pcle">эк</l>
      </lg>
      <mg><tg xml:lang="rus">
            <t>частица ишь</t>
         </tg>;<xg>
            <x1>эк сон мезе ёрай ишь чего захотел</x1>
         </xg></mg>
   </e>
   <e>
      <lg>
         <l pos="Pcle">эка</l>
      </lg>
      <mg>частица 1) <variants>
            <l_syn>эк </l_syn>
         </variants></mg>
      <mg><tg xml:lang="rus">
            <t> дай-ка, давай</t>
         </tg>;<xg>
            <x>эка суморгодан</x>
            <xt xml:lang="rus">дай-ка вздремну</xt>
         </xg></mg>
   </e>
   <e>
      <lg>
         <l pos="Pcle">экода</l>
      </lg>
      <mg>частица <range>Зубл- Пол.</range> пусть; экода моли пусть пойдёт</mg>
   </e>
   <e>
      <lg>
         <l pos="Pcle">эле</l>
      </lg>
      <mg><tg xml:lang="rus">
            <t>частица да, ну</t>
         </tg>;<xg>
            <x>-- Кинос молят? - Эле, молян</x>
            <xt xml:lang="rus">В кино пойдёшь? -- Да, пойду</xt>
         </xg></mg>
   </e>
   <e>
      <lg>
         <l pos="Pcle">эрь</l>
      </lg>
      <mg><tg xml:lang="rus">
            <t>частица ну</t>
         </tg><xg>
            <x src="В. Лёвин, Аера варма">Эрь, мес бта левоженнят</x>
            <xt xml:lang="rus">Ну, ты что как пьяный? </xt>
         </xg><ltgt/><xg>
            <x>эрь мезне</x>
            <xt xml:lang="rus">постоянно, всегда</xt>
         </xg>;<xg>
            <x1>эрь мезне сюци эсон всегда ругает меня</x1>
         </xg></mg>
   </e>
</r>
